<Hoc_sinh Ho_ten="Bạch phước bảo Châu" Ma_so="HS_316" CMND="070441104" Gioi_tinh="Nữ" Ngay_sinh="5/1/2004" Dia_chi="539 Hứa duy Hạnh,Phường 7,Quận 10, Ho Chi Minh City, Ho Chi Minh, Vietnam" Ten_Dang_nhap="HS_316" Mat_khau="HS_316">
  <Lop Ten="Lớp 7.4" Ma_so="LOP_7.4">
    <Khoi Ten="Khối 7" Ma_so="KHOI_7"/>
  </Lop>
  <Danh_sach_Vang>
    <Vang Ngay="6/10/2017" Ly_do="Không lý do"/>
    <Vang Ngay="2/10/2017" Ly_do="việc nhà"/>
    <Vang Ngay="3/9/2017" Ly_do="việc nhà"/>
    <Vang Ngay="3/10/2017" Ly_do="việc nhà"/>
    <Vang Ngay="1/9/2017" Ly_do="Không lý do"/>
    <Vang Ngay="4/9/2017" Ly_do="Không lý do"/>
  </Danh_sach_Vang>
</Hoc_sinh>